hyperoptax/__init__.py
hyperoptax/acquisition.py
hyperoptax/base.py
hyperoptax/bayesian.py
hyperoptax/grid.py
hyperoptax/kernels.py
hyperoptax/spaces.py
hyperoptax-0.1.6.dist-info/licenses/LICENSE
hyperoptax-0.1.6.dist-info/METADATA
hyperoptax-0.1.6.dist-info/WHEEL
hyperoptax-0.1.6.dist-info/top_level.txt
hyperoptax-0.1.6.dist-info/RECORD
