Metadata-Version: 2.4
Name: hyperoptax
Version: 0.1.6
Summary: Tuning hyperparameters with JAX
Author: Theo Wolf
License-Expression: Apache-2.0
Requires-Python: >=3.10
License-File: LICENSE
Requires-Dist: jax>=0.4.38
Provides-Extra: notebooks
Requires-Dist: flax; extra == "notebooks"
Requires-Dist: jupyter; extra == "notebooks"
Requires-Dist: matplotlib; extra == "notebooks"
Requires-Dist: notebook; extra == "notebooks"
Requires-Dist: rejax>=0.1.2; extra == "notebooks"
Requires-Dist: tqdm; extra == "notebooks"
Requires-Dist: bayesian-optimization; extra == "notebooks"
Requires-Dist: bayex; extra == "notebooks"
Provides-Extra: testing
Requires-Dist: pytest>=8.4.1; extra == "testing"
Requires-Dist: pytest-cov>=6.2.1; extra == "testing"
Provides-Extra: dev
Requires-Dist: ruff; extra == "dev"
Requires-Dist: mypy; extra == "dev"
Requires-Dist: pre-commit; extra == "dev"
Provides-Extra: all
Requires-Dist: hyperoptax[dev,notebooks,testing]; extra == "all"
Dynamic: license-file
